{
    "//Outline for tasks, non-highlighted GUI elements, unchecked boxes": [],
    "GUI_OUTLINE": [186, 140, 198, 255],

    "//Outline for highlighted GUI elements, checked boxes, icon colors": [],
    "GUI_OUTLINE_HIGHLIGHTED": [232, 115, 175, 255],

    "//Outline for disabled GUI elements / when clicking GUI elements":[],
    "GUI_OUTLINE_DISABLED": [232, 68, 169, 255],

    "//Inside for tasks, GUI background, background grid markers, axes on background grid": [],
    "GUI_INSIDE": [26, 20, 29, 255],

    "//Inside for highlighted GUI elements, completed Tasks": [],
    "GUI_INSIDE_HIGHLIGHTED": [84, 67, 95, 255],

    "//Inside for disabled GUI elements, grid background":[],
    "GUI_INSIDE_DISABLED": [0, 0, 0, 255],

    "//Text color":[],
    "GUI_FONT_COLOR": [255, 255, 255, 255],

    "//Note Tasks":[],
    "GUI_NOTE_COLOR": [26, 20, 29, 255],

    "//Task Shadows":[],
    "GUI_SHADOW_COLOR": [80, 81, 112, 255]
}
